{
        "DrifterMod:DexDownPower": {
                "NAME": "Dex Down",
                "DESCRIPTIONS": [
                        "Lose #b Dexterity at the end of the turn.",
                        "",
                        ""
                ]
        },
        "DrifterMod:DexterityNextTurnPower": {
                "NAME": "Dex Next Turn",
                "DESCRIPTIONS": [
                        "Gain #b Dexterity next turn.",
                        "",
                        ""
                ]
        },
        "DrifterMod:DriftingPower": {
                "NAME": "Drifting...",
                "DESCRIPTIONS": [
                        "Maintains your drift. If you don't have this, lose all your Drift at the end of the turn.",
                        "",
                        ""
                ]
        },
        "DrifterMod:DriftPower": {
                "NAME": "Drift",
                "DESCRIPTIONS": [
                        "Gain #b block and deal #b damage to all enemies at the end of the turn.",
                        "",
                        ""
                ]
        },
        "DrifterMod:TempRetainPower": {
                "NAME": "Retain",
                "DESCRIPTIONS": [
                        "Keep #b cards in your hand this turn only.",
                        "",
                        ""
                ]
        }
}